odoo10_addon_account_voucher_killer-10.0.1.0.0.99.dev1-py2.7-nspkg.pth
odoo/addons/account_voucher_killer/README.rst
odoo/addons/account_voucher_killer/__init__.py
odoo/addons/account_voucher_killer/__manifest__.py
odoo/addons/account_voucher_killer/i18n/account_voucher_killer.pot
odoo/addons/account_voucher_killer/i18n/es.po
odoo/addons/account_voucher_killer/i18n/pt_BR.po
odoo/addons/account_voucher_killer/i18n/sl.po
odoo/addons/account_voucher_killer/security/invoice_data.xml
odoo/addons/account_voucher_killer/static/description/icon.png
odoo/addons/account_voucher_killer/view/invoice_view.xml
odoo10_addon_account_voucher_killer-10.0.1.0.0.99.dev1.dist-info/DESCRIPTION.rst
odoo10_addon_account_voucher_killer-10.0.1.0.0.99.dev1.dist-info/METADATA
odoo10_addon_account_voucher_killer-10.0.1.0.0.99.dev1.dist-info/RECORD
odoo10_addon_account_voucher_killer-10.0.1.0.0.99.dev1.dist-info/WHEEL
odoo10_addon_account_voucher_killer-10.0.1.0.0.99.dev1.dist-info/metadata.json
odoo10_addon_account_voucher_killer-10.0.1.0.0.99.dev1.dist-info/namespace_packages.txt
odoo10_addon_account_voucher_killer-10.0.1.0.0.99.dev1.dist-info/top_level.txt
